LICENSE
MANIFEST.in
README.rst
pyproject.toml
setup.cfg
setup.py
django_user_auth_asl.egg-info/PKG-INFO
django_user_auth_asl.egg-info/SOURCES.txt
django_user_auth_asl.egg-info/dependency_links.txt
django_user_auth_asl.egg-info/requires.txt
django_user_auth_asl.egg-info/top_level.txt
user/__init__.py
user/admin.py
user/apps.py
user/models.py
user/serializers.py
user/tests.py
user/urls.py
user/views.py
user/migrations/0001_initial.py
user/migrations/__init__.py
user/templates/email/user_reset_password.html
user/templates/email/user_reset_password.txt